seequell/__init__.py
seequell/analyzers/base.py
seequell/analyzers/duplicates.py
seequell/analyzers/metrics.py
seequell/analyzers/slow_queries.py
seequell/config.py
seequell/middleware.py
seequell/query.py
seequell/utils.py
seequell-0.1.0.dist-info/LICENSE
seequell-0.1.0.dist-info/METADATA
seequell-0.1.0.dist-info/WHEEL
seequell-0.1.0.dist-info/RECORD
