Metadata-Version: 2.3
Name: seequell
Version: 0.1.0
Summary: 
Author: Nick Fuller
Author-email: nick@pfsbc.com
Requires-Python: >=3.12
Classifier: Programming Language :: Python :: 3
Classifier: Programming Language :: Python :: 3.12
Classifier: Programming Language :: Python :: 3.13
Requires-Dist: rich (>=14.0.0,<15.0.0)
Requires-Dist: sqlparse (>=0.5.0,<0.6.0)
